faster_dj_dev/__init__.py
faster_dj_dev/faster_dj.py
faster_dj_dev/codebase/__init__.py
faster_dj_dev/codebase/html_base_code.py
faster_dj_dev/codebase/instructions.py
faster_dj_dev/codebase/python_code_base.py
faster_dj_dev/commands/__init__.py
faster_dj_dev/commands/pyCommand.py
faster_dj_dev/core/__init__.py
faster_dj_dev/core/dj.py
faster_dj_dev/data/Pydata.py
faster_dj_dev/data/__init__.py
faster_dj_dev/data/config.json
faster_dj_dev/starter/__init__.py
faster_dj_dev/starter/starter.py
faster_dj_dev/utils/__init__.py
faster_dj_dev/utils/pyUtils.py
faster_dj_dev/venvs/Pyenv.py
faster_dj_dev/venvs/__init__.py
faster_dj_dev-0.1.7.dist-info/LICENSE
faster_dj_dev-0.1.7.dist-info/METADATA
faster_dj_dev-0.1.7.dist-info/WHEEL
faster_dj_dev-0.1.7.dist-info/entry_points.txt
faster_dj_dev-0.1.7.dist-info/top_level.txt
faster_dj_dev-0.1.7.dist-info/RECORD
