Metadata-Version: 2.1
Name: faster-dj-dev
Version: 0.1.7
Summary: A tool that makes your Django development faster.
Home-page: https://github.com/SelmiAbderrahim/faster-dj-dev
Author: Selmi Abderrahim
Author-email: contact@selmi.tech
License: MIT
Project-URL: Bug Tracker, https://github.com/SelmiAbderrahim/faster-dj-dev/issues
Keywords: django productivity automation fast development
Platform: UNKNOWN
Classifier: Development Status :: 3 - Alpha
Classifier: Intended Audience :: Developers
Classifier: Topic :: Software Development :: Build Tools
Classifier: License :: OSI Approved :: MIT License
Classifier: Programming Language :: Python :: 3.7
Classifier: Programming Language :: Python :: 3.8
Classifier: Programming Language :: Python :: 3.9
Classifier: Programming Language :: Python :: 3.10
License-File: LICENSE
Requires-Dist: yapf (==0.32.0)
Requires-Dist: click (==8.1.0)
Requires-Dist: colorama (==0.4.4)
Requires-Dist: termcolor (==1.1.0)
